setup.py
robostrippy/__init__.py
robostrippy/http.py
robostrippy/resource.py
robostrippy/utils.py
robostrippy.egg-info/PKG-INFO
robostrippy.egg-info/SOURCES.txt
robostrippy.egg-info/dependency_links.txt
robostrippy.egg-info/requires.txt
robostrippy.egg-info/top_level.txt