Metadata-Version: 1.1
Name: robostrippy
Version: 0.8
Summary: Strip HTML websites as though they provided a REST interface.  Like a Robot.
Home-page: http://github.com/bmuller/robostrippy
Author: Brian Muller
Author-email: bamuller@gmail.com
License: MIT
Platform: UNKNOWN
Requires: bs4.BeautifulSoup
Requires: requests
